README.md
setup.cfg
setup.py
distry/Binomialdistribution.py
distry/Gaussiandistribution.py
distry/Generaldistribution.py
distry/__init__.py
distry.egg-info/PKG-INFO
distry.egg-info/SOURCES.txt
distry.egg-info/dependency_links.txt
distry.egg-info/not-zip-safe
distry.egg-info/top_level.txt